jetpwmon/__init__.py
jetpwmon/_core.cpython-310-aarch64-linux-gnu.so
jetpwmon/cli.py
jetpwmon-0.1.2.dist-info/METADATA
jetpwmon-0.1.2.dist-info/WHEEL
jetpwmon-0.1.2.dist-info/top_level.txt
jetpwmon-0.1.2.dist-info/RECORD
jetpwmon-0.1.2.dist-info/licenses/LICENSE
