Metadata-Version: 2.4
Name: jetpwmon
Version: 0.1.2
Summary: A simple power monitor for Jetson
Author: Qi Deng
Author-email: Qi Deng <dengqi935@gmail.com>
Keywords: jetson,power,monitor,nvidia,nvidia-jetson,jetson-power-monitor
Requires-Python: >=3.7
License-File: LICENSE
Requires-Dist: pybind11>=2.9.0
Provides-Extra: dev
Requires-Dist: pytest>=8.3.5; extra == "dev"
Requires-Dist: black>=25.1.0; extra == "dev"
Requires-Dist: build>=0.10.0; extra == "dev"
Requires-Dist: pyyaml>=6.0.2; extra == "dev"
Requires-Dist: lark>=1.2.2; extra == "dev"
Provides-Extra: cli
Requires-Dist: rich>=13.9.4; extra == "cli"
Dynamic: author
Dynamic: license-file
Dynamic: requires-python
